agents/__init__.py
agents/architecture_agent.py
agents/code_quality_agent.py
agents/dependency_agent.py
agents/manager_agent.py
agents/performance_agent.py
agents/static_agent.py
butterfly/__init__.py
butterfly/cli.py
butterfly/core.py
gui-service/__init__.py
gui-service/main.py
gui-service/message_broker.py
gui-service/websocket_server.py
utils/__init__.py
utils/api_client.py
utils/api_key_manager.py
utils/cli_helpers.py
utils/config_manager.py
utils/encryption_utils.py
utils/env_manager.py
utils/visual_utils.py
butterfly_cli-0.0.1.dist-info/METADATA
butterfly_cli-0.0.1.dist-info/WHEEL
butterfly_cli-0.0.1.dist-info/entry_points.txt
butterfly_cli-0.0.1.dist-info/top_level.txt
butterfly_cli-0.0.1.dist-info/RECORD
