Metadata-Version: 2.1
Name: butterfly-cli
Version: 0.0.1
Summary: A security analysis tool using AI agents
Home-page: https://github.com/saint0x/butterfly-cli
Author: saint0x
Author-email: saint0x@example.com
Classifier: Development Status :: 3 - Alpha
Classifier: Intended Audience :: Developers
Classifier: License :: OSI Approved :: MIT License
Classifier: Operating System :: OS Independent
Classifier: Programming Language :: Python :: 3
Classifier: Programming Language :: Python :: 3.7
Classifier: Programming Language :: Python :: 3.8
Classifier: Programming Language :: Python :: 3.9
Classifier: Programming Language :: Python :: 3.10
Classifier: Programming Language :: Python :: 3.11
Classifier: Programming Language :: Python :: 3.12
Requires-Python: >=3.7
Requires-Dist: click
Requires-Dist: cryptography
Requires-Dist: python-dotenv
Requires-Dist: openai
Requires-Dist: rich
